[
    "26B | 26C",
    {
        "cx": 239,
        "cy": 343,
        "rx": 21.5,
        "ry": 31.0,
        "angle": 0,
        "label": "Appearance",
        "comment": ""
    },
    {
        "cx": 418,
        "cy": 193,
        "rx": 34.0,
        "ry": 34.0,
        "angle": 0,
        "label": "Appearance",
        "comment": ""
    },
    {
        "cx": 123,
        "cy": 539,
        "rx": 15.5,
        "ry": 30.5,
        "angle": 0,
        "label": "Appearance",
        "comment": ""
    }
]